geo/__init__.py
geo/color/__init__.py
geo/color/color.py
geo/data/__init__.py
geo/error/__init__.py
geo/error/value_error/__init__.py
geo/error/value_error/invalid_hex_error.py
geo/error/value_error/out_of_bounds_error.py
geo/error/value_error/out_of_singapore_error.py
geo/geom/__init__.py
geo/geom/distance.py
geo/geom/elevation.py
geo/geom/geo_pt.py
geo/geom/line.py
geo/geom/pointable.py
geo/geom/pt.py
geo/geom/shape.py
geo/geom/assets/singapore-elevation.png
geo/locations/__init__.py
geo/locations/bus_stop.py
geo/locations/halal.py
geo/locations/land_use.py
geo/locations/location.py
geo/locations/mall.py
geo/locations/network.py
geo/locations/planning.py
geo/locations/road.py
geo/locations/school.py
geo/locations/assets/.DS_Store
geo/locations/assets/MRT_Route_Map_CR.png
geo/locations/assets/MRT_Route_Map_CR_phase_1.png
geo/locations/assets/Train_Station_Exit_Layer.shp
geo/locations/assets/bus.csv
geo/locations/assets/halals.csv
geo/locations/assets/mall_planning.pickle
geo/locations/assets/mall_shapes.pickle
geo/locations/assets/malls.csv
geo/locations/assets/malls.pickle
geo/locations/assets/master-plan-2019-subzone-boundary-no-sea-kml.kml
geo/locations/assets/mrt.csv
geo/locations/assets/planning_area.pickle
geo/locations/assets/school_planning.pickle
geo/locations/assets/school_shapes.pickle
geo/locations/assets/schools.csv
geo/locations/mrt/__init__.py
geo/locations/mrt/connection.py
geo/locations/mrt/exit.py
geo/locations/mrt/mrt_line.py
geo/locations/mrt/platform.py
geo/locations/mrt/platform_code.py
geo/locations/mrt/station.py
geo/locations/mrt/assets/.DS_Store
geo/locations/mrt/assets/mrt-line.kml
geo/locations/mrt/assets/mrt.csv
geo/structures/__init__.py
geo/structures/avltree.py
geo/structures/avltree_v2.py
geo/structures/bound.py
geo/structures/bounds_tree.py
geo/structures/comparable.py
geo/structures/kdtree.py
geo/structures/pq.py
geo/structures/pq_v2.py
geo/structures/quick_sort.py
geo/utils/__init__.py
geo/utils/float.py
halfgeo-1.0.13.dist-info/LICENSE.txt
halfgeo-1.0.13.dist-info/METADATA
halfgeo-1.0.13.dist-info/WHEEL
halfgeo-1.0.13.dist-info/top_level.txt
halfgeo-1.0.13.dist-info/RECORD
