Metadata-Version: 2.1
Name: halfgeo
Version: 1.0.13
Home-page: https://github.com/mynameizzhafeez/geo
Author: Izz Hafeez
Author-email: izzhafeez@gmail.com
License: MIT
Keywords: geospatial singapore
License-File: LICENSE.txt
Requires-Dist: pandas
Requires-Dist: geopandas
Requires-Dist: numpy
Requires-Dist: shapely
Requires-Dist: gsheets
Requires-Dist: Pillow
Requires-Dist: fiona
